{
  "0x0": {
    "id": 0,
    "count": 2,
    "_offset": "0x1d8",
    "_end": "0x220",
    "blocks": [
      {
        "unknown1": -1,
        "unknown2": -1,
        "unknown3": 10,
        "x": 5,
        "y": 0,
        "z": 0,
        "radius": 25,
        "unknown8": 3
      },
      {
        "unknown1": -1,
        "unknown2": -1,
        "unknown3": 11,
        "x": 5,
        "y": 0,
        "z": 0,
        "radius": 30,
        "unknown8": 3
      }
    ]
  },
  "0x1": {
    "id": 1,
    "count": 2,
    "_offset": "0x220",
    "_end": "0x268",
    "blocks": [
      {
        "unknown1": -1,
        "unknown2": -1,
        "unknown3": 14,
        "x": 5,
        "y": 0,
        "z": 0,
        "radius": 25,
        "unknown8": 3
      },
      {
        "unknown1": -1,
        "unknown2": -1,
        "unknown3": 15,
        "x": 5,
        "y": 0,
        "z": 0,
        "radius": 30,
        "unknown8": 3
      }
    ]
  },
  "0x2": {
    "id": 2,
    "count": 2,
    "_offset": "0x268",
    "_end": "0x2b0",
    "blocks": [
      {
        "unknown1": -1,
        "unknown2": -1,
        "unknown3": 17,
        "x": 0,
        "y": 0,
        "z": 0,
        "radius": 40,
        "unknown8": 3
      },
      {
        "unknown1": -1,
        "unknown2": -1,
        "unknown3": 18,
        "x": 0,
        "y": 0,
        "z": 0,
        "radius": 40,
        "unknown8": 3
      }
    ]
  },
  "0x3": {
    "id": 3,
    "count": 2,
    "_offset": "0x2b0",
    "_end": "0x2f8",
    "blocks": [
      {
        "unknown1": -1,
        "unknown2": -1,
        "unknown3": 21,
        "x": 0,
        "y": 0,
        "z": 0,
        "radius": 40,
        "unknown8": 3
      },
      {
        "unknown1": -1,
        "unknown2": -1,
        "unknown3": 22,
        "x": 0,
        "y": 0,
        "z": 0,
        "radius": 40,
        "unknown8": 3
      }
    ]
  },
  "0x4": {
    "id": 4,
    "count": 2,
    "_offset": "0x2f8",
    "_end": "0x340",
    "blocks": [
      {
        "unknown1": -1,
        "unknown2": -1,
        "unknown3": 17,
        "x": 0,
        "y": 0,
        "z": 0,
        "radius": 27,
        "unknown8": 3
      },
      {
        "unknown1": -1,
        "unknown2": -1,
        "unknown3": 18,
        "x": 0,
        "y": 0,
        "z": 0,
        "radius": 33,
        "unknown8": 3
      }
    ]
  },
  "0x5": {
    "id": 5,
    "count": 1,
    "_offset": "0x340",
    "_end": "0x368",
    "blocks": [
      {
        "unknown1": -1,
        "unknown2": -1,
        "unknown3": 3,
        "x": 0,
        "y": 0,
        "z": 0,
        "radius": 750,
        "unknown8": 3
      }
    ]
  },
  "0x6": {
    "id": 6,
    "count": 2,
    "_offset": "0x368",
    "_end": "0x3b0",
    "blocks": [
      {
        "unknown1": -1,
        "unknown2": -1,
        "unknown3": 10,
        "x": 5,
        "y": 0,
        "z": 0,
        "radius": 25,
        "unknown8": 3
      },
      {
        "unknown1": -1,
        "unknown2": -1,
        "unknown3": 11,
        "x": 5,
        "y": 0,
        "z": 0,
        "radius": 40,
        "unknown8": 3
      }
    ]
  },
  "0x7": {
    "id": 7,
    "count": 0,
    "_offset": "0x3b0",
    "_end": "0x3b8",
    "blocks": []
  },
  "0x8": {
    "id": 8,
    "count": 0,
    "_offset": "0x3b8",
    "_end": "0x3c0",
    "blocks": []
  },
  "0x9": {
    "id": 9,
    "count": 1,
    "_offset": "0x3c0",
    "_end": "0x3e8",
    "blocks": [
      {
        "unknown1": -1,
        "unknown2": -1,
        "unknown3": -1,
        "x": 0,
        "y": 140,
        "z": 23,
        "radius": 40,
        "unknown8": 3
      }
    ]
  },
  "0xa": {
    "id": 10,
    "count": 3,
    "_offset": "0x3e8",
    "_end": "0x450",
    "blocks": [
      {
        "unknown1": -1,
        "unknown2": -1,
        "unknown3": -1,
        "x": 0,
        "y": 0,
        "z": 20,
        "radius": 40,
        "unknown8": 3
      },
      {
        "unknown1": -1,
        "unknown2": -1,
        "unknown3": -1,
        "x": 0,
        "y": 50,
        "z": 20,
        "radius": 40,
        "unknown8": 3
      },
      {
        "unknown1": -1,
        "unknown2": -1,
        "unknown3": -1,
        "x": 0,
        "y": 100,
        "z": 20,
        "radius": 40,
        "unknown8": 3
      }
    ]
  },
  "0xb": {
    "id": 11,
    "count": 1,
    "_offset": "0x450",
    "_end": "0x478",
    "blocks": [
      {
        "unknown1": -1,
        "unknown2": -1,
        "unknown3": 15,
        "x": 0,
        "y": 0,
        "z": 0,
        "radius": 28,
        "unknown8": 3
      }
    ]
  },
  "0xc": {
    "id": 12,
    "count": 1,
    "_offset": "0x478",
    "_end": "0x4a0",
    "blocks": [
      {
        "unknown1": -1,
        "unknown2": -1,
        "unknown3": 11,
        "x": 5,
        "y": 0,
        "z": 0,
        "radius": 28,
        "unknown8": 3
      }
    ]
  },
  "0xd": {
    "id": 13,
    "count": 1,
    "_offset": "0x4a0",
    "_end": "0x4c8",
    "blocks": [
      {
        "unknown1": -1,
        "unknown2": -1,
        "unknown3": 18,
        "x": 0,
        "y": 0,
        "z": 0,
        "radius": 35,
        "unknown8": 3
      }
    ]
  },
  "0xe": {
    "id": 14,
    "count": 1,
    "_offset": "0x4c8",
    "_end": "0x4f0",
    "blocks": [
      {
        "unknown1": -1,
        "unknown2": -1,
        "unknown3": 22,
        "x": 0,
        "y": 0,
        "z": 0,
        "radius": 33,
        "unknown8": 3
      }
    ]
  },
  "0xf": {
    "id": 15,
    "count": 2,
    "_offset": "0x4f0",
    "_end": "0x538",
    "blocks": [
      {
        "unknown1": -1,
        "unknown2": -1,
        "unknown3": 14,
        "x": 5,
        "y": 0,
        "z": 0,
        "radius": 25,
        "unknown8": 3
      },
      {
        "unknown1": -1,
        "unknown2": -1,
        "unknown3": 15,
        "x": 5,
        "y": 0,
        "z": 0,
        "radius": 35,
        "unknown8": 3
      }
    ]
  },
  "0x10": {
    "id": 16,
    "count": 2,
    "_offset": "0x538",
    "_end": "0x580",
    "blocks": [
      {
        "unknown1": -1,
        "unknown2": -1,
        "unknown3": 17,
        "x": 0,
        "y": 0,
        "z": 0,
        "radius": 30,
        "unknown8": 3
      },
      {
        "unknown1": -1,
        "unknown2": -1,
        "unknown3": 18,
        "x": 0,
        "y": 0,
        "z": 0,
        "radius": 35,
        "unknown8": 3
      }
    ]
  },
  "0x11": {
    "id": 17,
    "count": 2,
    "_offset": "0x580",
    "_end": "0x5c8",
    "blocks": [
      {
        "unknown1": -1,
        "unknown2": -1,
        "unknown3": 21,
        "x": 0,
        "y": 0,
        "z": 0,
        "radius": 25,
        "unknown8": 3
      },
      {
        "unknown1": -1,
        "unknown2": -1,
        "unknown3": 22,
        "x": 0,
        "y": 0,
        "z": 0,
        "radius": 30,
        "unknown8": 3
      }
    ]
  },
  "0x12": {
    "id": 18,
    "count": 2,
    "_offset": "0x5c8",
    "_end": "0x610",
    "blocks": [
      {
        "unknown1": -1,
        "unknown2": -1,
        "unknown3": 17,
        "x": 0,
        "y": 0,
        "z": 0,
        "radius": 27,
        "unknown8": 3
      },
      {
        "unknown1": -1,
        "unknown2": -1,
        "unknown3": 18,
        "x": 0,
        "y": 0,
        "z": 0,
        "radius": 33,
        "unknown8": 3
      }
    ]
  },
  "0x13": {
    "id": 19,
    "count": 2,
    "_offset": "0x610",
    "_end": "0x658",
    "blocks": [
      {
        "unknown1": -1,
        "unknown2": -1,
        "unknown3": 14,
        "x": 5,
        "y": 0,
        "z": 0,
        "radius": 25,
        "unknown8": 3
      },
      {
        "unknown1": -1,
        "unknown2": -1,
        "unknown3": 15,
        "x": 5,
        "y": 0,
        "z": 0,
        "radius": 40,
        "unknown8": 3
      }
    ]
  },
  "0x14": {
    "id": 20,
    "count": 2,
    "_offset": "0x658",
    "_end": "0x6a0",
    "blocks": [
      {
        "unknown1": -1,
        "unknown2": -1,
        "unknown3": 21,
        "x": 0,
        "y": 0,
        "z": 0,
        "radius": 40,
        "unknown8": 3
      },
      {
        "unknown1": -1,
        "unknown2": -1,
        "unknown3": 22,
        "x": 0,
        "y": 0,
        "z": 0,
        "radius": 40,
        "unknown8": 3
      }
    ]
  },
  "0x15": {
    "id": 21,
    "count": 2,
    "_offset": "0x6a0",
    "_end": "0x6e8",
    "blocks": [
      {
        "unknown1": -1,
        "unknown2": -1,
        "unknown3": 17,
        "x": 0,
        "y": 0,
        "z": 0,
        "radius": 30,
        "unknown8": 3
      },
      {
        "unknown1": -1,
        "unknown2": -1,
        "unknown3": 18,
        "x": 0,
        "y": 0,
        "z": 0,
        "radius": 35,
        "unknown8": 3
      }
    ]
  },
  "0x16": {
    "id": 22,
    "count": 1,
    "_offset": "0x6e8",
    "_end": "0x710",
    "blocks": [
      {
        "unknown1": -1,
        "unknown2": -1,
        "unknown3": 18,
        "x": 0,
        "y": 0,
        "z": 0,
        "radius": 45,
        "unknown8": 3
      }
    ]
  },
  "0x17": {
    "id": 23,
    "count": 1,
    "_offset": "0x710",
    "_end": "0x738",
    "blocks": [
      {
        "unknown1": -1,
        "unknown2": -1,
        "unknown3": 15,
        "x": 0,
        "y": 0,
        "z": 0,
        "radius": 60,
        "unknown8": 3
      }
    ]
  },
  "0x18": {
    "id": 24,
    "count": 2,
    "_offset": "0x738",
    "_end": "0x780",
    "blocks": [
      {
        "unknown1": -1,
        "unknown2": -1,
        "unknown3": 17,
        "x": 0,
        "y": 0,
        "z": 0,
        "radius": 40,
        "unknown8": 3
      },
      {
        "unknown1": -1,
        "unknown2": -1,
        "unknown3": 18,
        "x": 0,
        "y": 0,
        "z": 0,
        "radius": 40,
        "unknown8": 3
      }
    ]
  },
  "0x19": {
    "id": 25,
    "count": 0,
    "_offset": "0x780",
    "_end": "0x788",
    "blocks": []
  },
  "0x1a": {
    "id": 26,
    "count": 0,
    "_offset": "0x788",
    "_end": "0x790",
    "blocks": []
  },
  "0x1b": {
    "id": 27,
    "count": 0,
    "_offset": "0x790",
    "_end": "0x798",
    "blocks": []
  },
  "0x1c": {
    "id": 28,
    "count": 0,
    "_offset": "0x798",
    "_end": "0x7a0",
    "blocks": []
  },
  "0x1d": {
    "id": 29,
    "count": 0,
    "_offset": "0x7a0",
    "_end": "0x7a8",
    "blocks": []
  },
  "0x1e": {
    "id": 30,
    "count": 0,
    "_offset": "0x7a8",
    "_end": "0x7b0",
    "blocks": []
  },
  "0x1f": {
    "id": 31,
    "count": 0,
    "_offset": "0x7b0",
    "_end": "0x7b8",
    "blocks": []
  },
  "0x20": {
    "id": 32,
    "count": 0,
    "_offset": "0x7b8",
    "_end": "0x7c0",
    "blocks": []
  },
  "0x21": {
    "id": 33,
    "count": 0,
    "_offset": "0x7c0",
    "_end": "0x7c8",
    "blocks": []
  },
  "0x22": {
    "id": 34,
    "count": 0,
    "_offset": "0x7c8",
    "_end": "0x7d0",
    "blocks": []
  },
  "0x23": {
    "id": 35,
    "count": 0,
    "_offset": "0x7d0",
    "_end": "0x7d8",
    "blocks": []
  },
  "0x24": {
    "id": 36,
    "count": 0,
    "_offset": "0x7d8",
    "_end": "0x7e0",
    "blocks": []
  },
  "0x25": {
    "id": 37,
    "count": 0,
    "_offset": "0x7e0",
    "_end": "0x7e8",
    "blocks": []
  },
  "0x26": {
    "id": 38,
    "count": 0,
    "_offset": "0x7e8",
    "_end": "0x7f0",
    "blocks": []
  },
  "0x27": {
    "id": 39,
    "count": 2,
    "_offset": "0x7f0",
    "_end": "0x838",
    "blocks": [
      {
        "unknown1": -1,
        "unknown2": -1,
        "unknown3": 10,
        "x": 5,
        "y": 0,
        "z": 0,
        "radius": 25,
        "unknown8": 3
      },
      {
        "unknown1": -1,
        "unknown2": -1,
        "unknown3": 11,
        "x": 5,
        "y": 0,
        "z": 0,
        "radius": 40,
        "unknown8": 3
      }
    ]
  },
  "0x28": {
    "id": 40,
    "count": 2,
    "_offset": "0x838",
    "_end": "0x880",
    "blocks": [
      {
        "unknown1": -1,
        "unknown2": -1,
        "unknown3": 17,
        "x": 0,
        "y": 0,
        "z": 0,
        "radius": 40,
        "unknown8": 3
      },
      {
        "unknown1": -1,
        "unknown2": -1,
        "unknown3": 18,
        "x": 0,
        "y": 0,
        "z": 0,
        "radius": 50,
        "unknown8": 3
      }
    ]
  },
  "0x29": {
    "id": 41,
    "count": 2,
    "_offset": "0x880",
    "_end": "0x8c8",
    "blocks": [
      {
        "unknown1": -1,
        "unknown2": -1,
        "unknown3": 21,
        "x": 0,
        "y": 0,
        "z": 0,
        "radius": 40,
        "unknown8": 3
      },
      {
        "unknown1": -1,
        "unknown2": -1,
        "unknown3": 22,
        "x": 0,
        "y": 0,
        "z": 0,
        "radius": 40,
        "unknown8": 3
      }
    ]
  },
  "0x2a": {
    "id": 42,
    "count": 2,
    "_offset": "0x8c8",
    "_end": "0x910",
    "blocks": [
      {
        "unknown1": -1,
        "unknown2": -1,
        "unknown3": 17,
        "x": 0,
        "y": 0,
        "z": 0,
        "radius": 40,
        "unknown8": 3
      },
      {
        "unknown1": -1,
        "unknown2": -1,
        "unknown3": 18,
        "x": 0,
        "y": 0,
        "z": 0,
        "radius": 40,
        "unknown8": 3
      }
    ]
  },
  "0x2b": {
    "id": 43,
    "count": 2,
    "_offset": "0x910",
    "_end": "0x958",
    "blocks": [
      {
        "unknown1": -1,
        "unknown2": -1,
        "unknown3": 17,
        "x": 0,
        "y": 0,
        "z": 0,
        "radius": 40,
        "unknown8": 3
      },
      {
        "unknown1": -1,
        "unknown2": -1,
        "unknown3": 18,
        "x": 0,
        "y": 0,
        "z": 0,
        "radius": 50,
        "unknown8": 3
      }
    ]
  },
  "0x2c": {
    "id": 44,
    "count": 2,
    "_offset": "0x958",
    "_end": "0x9a0",
    "blocks": [
      {
        "unknown1": -1,
        "unknown2": -1,
        "unknown3": 21,
        "x": 0,
        "y": 0,
        "z": 0,
        "radius": 40,
        "unknown8": 3
      },
      {
        "unknown1": -1,
        "unknown2": -1,
        "unknown3": 22,
        "x": 0,
        "y": 0,
        "z": 0,
        "radius": 40,
        "unknown8": 3
      }
    ]
  },
  "0x2d": {
    "id": 45,
    "count": 2,
    "_offset": "0x9a0",
    "_end": "0x9e8",
    "blocks": [
      {
        "unknown1": -1,
        "unknown2": -1,
        "unknown3": 17,
        "x": 0,
        "y": 0,
        "z": 0,
        "radius": 40,
        "unknown8": 3
      },
      {
        "unknown1": -1,
        "unknown2": -1,
        "unknown3": 18,
        "x": 0,
        "y": 0,
        "z": 0,
        "radius": 40,
        "unknown8": 3
      }
    ]
  },
  "0x2e": {
    "id": 46,
    "count": 2,
    "_offset": "0x9e8",
    "_end": "0xa30",
    "blocks": [
      {
        "unknown1": -1,
        "unknown2": -1,
        "unknown3": 17,
        "x": 0,
        "y": 0,
        "z": 0,
        "radius": 40,
        "unknown8": 3
      },
      {
        "unknown1": -1,
        "unknown2": -1,
        "unknown3": 18,
        "x": 0,
        "y": 0,
        "z": 0,
        "radius": 40,
        "unknown8": 3
      }
    ]
  },
  "0x2f": {
    "id": 47,
    "count": 2,
    "_offset": "0xa30",
    "_end": "0xa78",
    "blocks": [
      {
        "unknown1": -1,
        "unknown2": -1,
        "unknown3": 21,
        "x": 0,
        "y": 0,
        "z": 0,
        "radius": 40,
        "unknown8": 3
      },
      {
        "unknown1": -1,
        "unknown2": -1,
        "unknown3": 22,
        "x": 0,
        "y": 0,
        "z": 0,
        "radius": 40,
        "unknown8": 3
      }
    ]
  },
  "0x30": {
    "id": 48,
    "count": 2,
    "_offset": "0xa78",
    "_end": "0xac0",
    "blocks": [
      {
        "unknown1": -1,
        "unknown2": -1,
        "unknown3": 17,
        "x": 0,
        "y": 0,
        "z": 0,
        "radius": 60,
        "unknown8": 3
      },
      {
        "unknown1": -1,
        "unknown2": -1,
        "unknown3": 18,
        "x": 0,
        "y": 0,
        "z": 0,
        "radius": 60,
        "unknown8": 3
      }
    ]
  },
  "0x31": {
    "id": 49,
    "count": 1,
    "_offset": "0xac0",
    "_end": "0xae8",
    "blocks": [
      {
        "unknown1": -1,
        "unknown2": -1,
        "unknown3": 11,
        "x": 5,
        "y": 0,
        "z": 0,
        "radius": 30,
        "unknown8": 3
      }
    ]
  },
  "0x32": {
    "id": 50,
    "count": 2,
    "_offset": "0xae8",
    "_end": "0xb30",
    "blocks": [
      {
        "unknown1": -1,
        "unknown2": -1,
        "unknown3": 21,
        "x": 0,
        "y": 0,
        "z": 0,
        "radius": 40,
        "unknown8": 3
      },
      {
        "unknown1": -1,
        "unknown2": -1,
        "unknown3": 22,
        "x": 0,
        "y": 0,
        "z": 0,
        "radius": 40,
        "unknown8": 3
      }
    ]
  },
  "0x33": {
    "id": 51,
    "count": 2,
    "_offset": "0xb30",
    "_end": "0xb78",
    "blocks": [
      {
        "unknown1": -1,
        "unknown2": -1,
        "unknown3": 17,
        "x": 0,
        "y": 0,
        "z": 40,
        "radius": 70,
        "unknown8": 3
      },
      {
        "unknown1": -1,
        "unknown2": -1,
        "unknown3": 18,
        "x": 0,
        "y": 0,
        "z": 40,
        "radius": 70,
        "unknown8": 3
      }
    ]
  },
  "0x34": {
    "id": 52,
    "count": 4,
    "_offset": "0xb78",
    "_end": "0xc00",
    "blocks": [
      {
        "unknown1": -1,
        "unknown2": -1,
        "unknown3": 17,
        "x": 0,
        "y": 0,
        "z": 0,
        "radius": 40,
        "unknown8": 3
      },
      {
        "unknown1": -1,
        "unknown2": -1,
        "unknown3": 18,
        "x": 0,
        "y": 0,
        "z": 0,
        "radius": 50,
        "unknown8": 3
      },
      {
        "unknown1": -1,
        "unknown2": -1,
        "unknown3": 21,
        "x": 0,
        "y": 0,
        "z": 0,
        "radius": 40,
        "unknown8": 3
      },
      {
        "unknown1": -1,
        "unknown2": -1,
        "unknown3": 22,
        "x": 0,
        "y": 0,
        "z": 0,
        "radius": 50,
        "unknown8": 3
      }
    ]
  },
  "0x35": {
    "id": 53,
    "count": 0,
    "_offset": "0xc00",
    "_end": "0xc08",
    "blocks": []
  },
  "0x36": {
    "id": 54,
    "count": 0,
    "_offset": "0xc08",
    "_end": "0xc10",
    "blocks": []
  },
  "0x37": {
    "id": 55,
    "count": 2,
    "_offset": "0xc10",
    "_end": "0xc58",
    "blocks": [
      {
        "unknown1": -1,
        "unknown2": -1,
        "unknown3": 17,
        "x": 0,
        "y": 0,
        "z": 0,
        "radius": 40,
        "unknown8": 3
      },
      {
        "unknown1": -1,
        "unknown2": -1,
        "unknown3": 18,
        "x": 0,
        "y": 0,
        "z": 0,
        "radius": 70,
        "unknown8": 3
      }
    ]
  },
  "0x38": {
    "id": 56,
    "count": 2,
    "_offset": "0xc58",
    "_end": "0xca0",
    "blocks": [
      {
        "unknown1": -1,
        "unknown2": -1,
        "unknown3": 17,
        "x": 0,
        "y": 0,
        "z": 0,
        "radius": 40,
        "unknown8": 3
      },
      {
        "unknown1": -1,
        "unknown2": -1,
        "unknown3": 18,
        "x": 0,
        "y": 0,
        "z": 0,
        "radius": 70,
        "unknown8": 3
      }
    ]
  }
}